idm/__init__.py
idm/idm.py
indomar-1.0.4.dist-info/METADATA
indomar-1.0.4.dist-info/WHEEL
indomar-1.0.4.dist-info/entry_points.txt
indomar-1.0.4.dist-info/top_level.txt
indomar-1.0.4.dist-info/RECORD
