Metadata-Version: 2.1
Name: indomar
Version: 1.0.4
Summary: hanya sebuah script biasa
Home-page: https://github.com/username/my_project
Author: robbi 13
Author-email: email@example.com
Requires-Dist: aiohttp
Requires-Dist: requests
